inline_ordering
