Metadata-Version: 1.1
Name: django-inline-ordering
Version: 1.0.2
Summary: Django app to ease ordering of related data - enable Drag&Drop ordering in admin with just a few LOC
Home-page: http://github.com/centralniak
Author: Piotr Kilczuk
Author-email: p.kilczuk@neumea.pl
License: UNKNOWN
Platform: UNKNOWN
Classifier: Framework :: Django
Classifier: Development Status :: 5 - Production/Stable
Classifier: Environment :: Web Environment
Classifier: Programming Language :: Python
Classifier: Intended Audience :: Developers
Classifier: Operating System :: OS Independent
Classifier: License :: OSI Approved :: BSD License
Classifier: Topic :: Software Development :: Libraries :: Python Modules
Provides: inline_ordering
